vrt_spacy/__init__.py
vrt_spacy-0.0.1.dist-info/LICENSE
vrt_spacy-0.0.1.dist-info/METADATA
vrt_spacy-0.0.1.dist-info/WHEEL
vrt_spacy-0.0.1.dist-info/top_level.txt
vrt_spacy-0.0.1.dist-info/RECORD
