Metadata-Version: 2.1
Name: vrt-spacy
Version: 0.0.1
Summary: creating vrt corpora
Home-page: https://github.com/miweru/vrt_spacy
Author: Michael Ruppert
Author-email: michael.ruppert@fau.de
License: GPL-3.0
Platform: UNKNOWN
Classifier: Programming Language :: Python :: 3
Classifier: License :: OSI Approved :: GNU General Public License v3 or later (GPLv3+)
Classifier: Topic :: Software Development :: Libraries :: Python Modules
Classifier: Topic :: Text Processing :: Linguistic
Requires-Python: >=3.5
Requires-Dist: smart-open (>=1.9.0)
Requires-Dist: spacy (>=2.2.3)
Requires-Dist: vrt-generator (>=0.0.6)
